ual/custom_operations.vhd
library IEEE;
use IEEE.STD_LOGIC_1164.ALL;
use IEEE.NUMERIC_STD.ALL;

-- Custom operations unit implementing 3 specific functions:
-- RES_OUT_1 = A * B (8-bit result)
-- RES_OUT_2 = A + B
-- RES_OUT_3 = (A xnor B[0]) or (A xnor B[1])
--
-- A result is computed and then held on RES_OUT until next START signal
-- RES_VALID indicates when result is ready (0=computing, 1=result available)

entity custom_operations is
    Port (
        clk         : in  STD_LOGIC;
        reset       : in  STD_LOGIC;
        start       : in  STD_LOGIC;              -- Start computation
        operation   : in  STD_LOGIC_VECTOR(1 downto 0);  -- Select operation (00=mult, 01=add, 10=xnor_logic)
        A           : in  STD_LOGIC_VECTOR(3 downto 0);
        B           : in  STD_LOGIC_VECTOR(3 downto 0);
        RES_OUT     : out STD_LOGIC_VECTOR(7 downto 0);  -- Result (0 while computing)
        RES_VALID   : out STD_LOGIC                      -- 0=computing, 1=result ready
    );
end custom_operations;

architecture Behavioral of custom_operations is
    
    -- State machine for result timing
    type state_type is (IDLE, COMPUTING, RESULT_READY);
    signal state : state_type := IDLE;
    
    -- Stored results
    signal result_buf : STD_LOGIC_VECTOR(7 downto 0) := (others => '0');
    signal operation_stored : STD_LOGIC_VECTOR(1 downto 0) := (others => '0');
    signal a_stored : STD_LOGIC_VECTOR(3 downto 0) := (others => '0');
    signal b_stored : STD_LOGIC_VECTOR(3 downto 0) := (others => '0');
    
    -- Computed result (combinational)
    signal computed_result : STD_LOGIC_VECTOR(7 downto 0);
    
begin
    
    -- Combinational computation of all 3 operations
    process(operation_stored, a_stored, b_stored)
        variable mult_result : unsigned(7 downto 0);
        variable add_result : unsigned(7 downto 0);
        variable xnor_result : STD_LOGIC_VECTOR(3 downto 0);
        variable final_result : STD_LOGIC_VECTOR(7 downto 0);
    begin
        -- Operation 1: Multiplication (A * B) -> 8 bits
        mult_result := unsigned(a_stored) * unsigned(b_stored);
        
        -- Operation 2: Addition (A + B) -> 8 bits (zero-extended)
        add_result := resize(unsigned(a_stored), 8) + resize(unsigned(b_stored), 8);
        
        -- Operation 3: (A xnor B[0]) or (A xnor B[1])
        -- This is a 4-bit result (A is 4 bits)
        xnor_result := (a_stored xnor (b_stored(0) & b_stored(0) & b_stored(0) & b_stored(0))) or
                       (a_stored xnor (b_stored(1) & b_stored(1) & b_stored(1) & b_stored(1)));
        
        -- Select operation result
        case operation_stored is
            when "00" =>  -- Multiplication
                final_result := std_logic_vector(mult_result);
            when "01" =>  -- Addition
                final_result := std_logic_vector(add_result);
            when "10" =>  -- XNOR logic
                final_result := (others => '0');
                final_result(3 downto 0) := xnor_result;  -- 4-bit result, upper bits = 0
            when others =>
                final_result := (others => '0');
        end case;
        
        computed_result <= final_result;
    end process;
    
    -- State machine: handle START signal and computation timing
    process(clk)
    begin
        if rising_edge(clk) then
            if reset = '1' then
                state <= IDLE;
                result_buf <= (others => '0');
                RES_VALID <= '0';
            else
                case state is
                    when IDLE =>
                        -- Wait for START signal
                        if start = '1' then
                            a_stored <= A;
                            b_stored <= B;
                            operation_stored <= operation;
                            state <= COMPUTING;
                            RES_VALID <= '0';
                            result_buf <= (others => '0');  -- Output is 0 during compute
                        else
                            RES_VALID <= '0';
                            result_buf <= (others => '0');
                        end if;
                    
                    when COMPUTING =>
                        -- Compute takes 1 cycle, then move to RESULT_READY
                        -- On next clock edge, result is available
                        result_buf <= computed_result;
                        state <= RESULT_READY;
                        RES_VALID <= '1';  -- Result is now ready
                    
                    when RESULT_READY =>
                        -- Hold result until next START
                        if start = '1' then
                            a_stored <= A;
                            b_stored <= B;
                            operation_stored <= operation;
                            state <= COMPUTING;
                            RES_VALID <= '0';
                            result_buf <= (others => '0');  -- Output is 0 during compute
                        else
                            -- Maintain current result
                            RES_VALID <= '1';
                        end if;
                    
                    when others =>
                        state <= IDLE;
                        RES_VALID <= '0';
                end case;
            end if;
        end if;
    end process;
    
    -- Output assignment
    RES_OUT <= result_buf;
    
end Behavioral;

projet/projet.srcs/sim_1/imports/ual/custom_operations_tb.vhd
library IEEE;
use IEEE.STD_LOGIC_1164.ALL;
use IEEE.NUMERIC_STD.ALL;

entity custom_operations_tb is
end custom_operations_tb;

architecture behavior of custom_operations_tb is

    component custom_operations
        Port (
            clk         : in  STD_LOGIC;
            reset       : in  STD_LOGIC;
            start       : in  STD_LOGIC;
            operation   : in  STD_LOGIC_VECTOR(1 downto 0);
            A           : in  STD_LOGIC_VECTOR(3 downto 0);
            B           : in  STD_LOGIC_VECTOR(3 downto 0);
            RES_OUT     : out STD_LOGIC_VECTOR(7 downto 0);
            RES_VALID   : out STD_LOGIC
        );
    end component;

    signal clk              : STD_LOGIC := '0';
    signal reset            : STD_LOGIC := '1';
    signal start_sig        : STD_LOGIC := '0';
    signal operation_sig    : STD_LOGIC_VECTOR(1 downto 0) := "00";
    signal A_sig            : STD_LOGIC_VECTOR(3 downto 0) := "0000";
    signal B_sig            : STD_LOGIC_VECTOR(3 downto 0) := "0000";
    signal RES_OUT_sig      : STD_LOGIC_VECTOR(7 downto 0);
    signal RES_VALID_sig    : STD_LOGIC;

begin

    uut: custom_operations
        port map (
            clk => clk,
            reset => reset,
            start => start_sig,
            operation => operation_sig,
            A => A_sig,
            B => B_sig,
            RES_OUT => RES_OUT_sig,
            RES_VALID => RES_VALID_sig
        );

    -- Clock generation
    clk_proc: process
    begin
        while True loop
            clk <= '0';
            wait for 5 ns;
            clk <= '1';
            wait for 5 ns;
        end loop;
    end process;

    -- Stimulus process
    stim_proc: process
    begin
        -- Reset
        reset <= '1';
        wait for 10 ns;
        reset <= '0';
        wait for 5 ns;

        -- Test 1: Multiplication (A=3, B=4) -> 12
        report "Test 1: A=3, B=4, Operation=MULT (00) -> Expected: 12";
        A_sig <= "0011";           -- 3
        B_sig <= "0100";           -- 4
        operation_sig <= "00";     -- Multiplication
        start_sig <= '1';
        wait for 10 ns;
        start_sig <= '0';
        wait for 10 ns;  -- First cycle: computing
        -- Result should be available now
        assert RES_VALID_sig = '1' report "RES_VALID should be 1 after compute cycle" severity error;
        assert unsigned(RES_OUT_sig) = 12 report "Result should be 12 (3*4)" severity error;
        report "Test 1 PASS: RES_OUT=" & integer'image(to_integer(unsigned(RES_OUT_sig))) & ", RES_VALID=" & std_logic'image(RES_VALID_sig);
        wait for 20 ns;

        -- Test 2: Addition (A=5, B=3) -> 8
        report "Test 2: A=5, B=3, Operation=ADD (01) -> Expected: 8";
        A_sig <= "0101";           -- 5
        B_sig <= "0011";           -- 3
        operation_sig <= "01";     -- Addition
        start_sig <= '1';
        wait for 10 ns;
        start_sig <= '0';
        wait for 10 ns;  -- First cycle: computing
        assert RES_VALID_sig = '1' report "RES_VALID should be 1 after compute cycle" severity error;
        assert unsigned(RES_OUT_sig) = 8 report "Result should be 8 (5+3)" severity error;
        report "Test 2 PASS: RES_OUT=" & integer'image(to_integer(unsigned(RES_OUT_sig))) & ", RES_VALID=" & std_logic'image(RES_VALID_sig);
        wait for 20 ns;

        -- Test 3: XNOR logic (A=1010, B=0011)
        -- (A xnor B[0]) or (A xnor B[1])
        -- B[0]=1, B[1]=1, so:
        -- (1010 xnor 1111) or (1010 xnor 1111) = 0101 or 0101 = 0101
        report "Test 3: A=1010, B=0011, Operation=XNOR_LOGIC (10) -> Expected: 0101";
        A_sig <= "1010";           -- A = 1010
        B_sig <= "0011";           -- B = 0011 (B[0]=1, B[1]=1)
        operation_sig <= "10";     -- XNOR logic
        start_sig <= '1';
        wait for 10 ns;
        start_sig <= '0';
        wait for 10 ns;  -- First cycle: computing
        assert RES_VALID_sig = '1' report "RES_VALID should be 1 after compute cycle" severity error;
        report "Test 3: RES_OUT=" & integer'image(to_integer(unsigned(RES_OUT_sig))) & ", RES_VALID=" & std_logic'image(RES_VALID_sig);
        wait for 20 ns;

        -- Test 4: Verify result is held without START
        report "Test 4: Verify result held (no START signal)";
        A_sig <= "1111";
        B_sig <= "0000";
        start_sig <= '0';
        wait for 20 ns;
        assert RES_VALID_sig = '1' report "RES_VALID should remain 1" severity error;
        report "Test 4 PASS: Result held correctly";
        wait for 20 ns;

        -- Test 5: Large multiplication
        report "Test 5: A=15, B=15, Operation=MULT (00) -> Expected: 225";
        A_sig <= "1111";           -- 15
        B_sig <= "1111";           -- 15
        operation_sig <= "00";     -- Multiplication
        start_sig <= '1';
        wait for 10 ns;
        start_sig <= '0';
        wait for 10 ns;  -- First cycle: computing
        assert RES_VALID_sig = '1' report "RES_VALID should be 1 after compute cycle" severity error;
        assert unsigned(RES_OUT_sig) = 225 report "Result should be 225 (15*15)" severity error;
        report "Test 5 PASS: RES_OUT=" & integer'image(to_integer(unsigned(RES_OUT_sig))) & ", RES_VALID=" & std_logic'image(RES_VALID_sig);
        wait for 20 ns;

        report "All tests completed successfully!";
        wait;
    end process;

end behavior;

ual/custom_ops.vcd
$date
  Mon May  4 10:19:31 2026
$end
$version
  GHDL v0
$end
$timescale
  1 fs
$end
$scope module standard $end
$upscope $end
$scope module textio $end
$upscope $end
$scope module std_logic_1164 $end
$upscope $end
$scope module numeric_std $end
$upscope $end
$scope module custom_operations_tb $end
$var reg 1 ! clk $end
$var reg 1 " reset $end
$var reg 1 # start_sig $end
$var reg 2 $ operation_sig[1:0] $end
$var reg 4 % a_sig[3:0] $end
$var reg 4 & b_sig[3:0] $end
$var reg 8 ' res_out_sig[7:0] $end
$var reg 1 ( res_valid_sig $end
$scope module uut $end
$var reg 1 ) clk $end
$var reg 1 * reset $end
$var reg 1 + start $end
$var reg 2 , operation[1:0] $end
$var reg 4 - a[3:0] $end
$var reg 4 . b[3:0] $end
$var reg 8 / res_out[7:0] $end
$var reg 1 0 res_valid $end
$comment state is not handled $end
$var reg 8 1 result_buf[7:0] $end
$var reg 2 2 operation_stored[1:0] $end
$var reg 4 3 a_stored[3:0] $end
$var reg 4 4 b_stored[3:0] $end
$var reg 8 5 computed_result[7:0] $end
$upscope $end
$upscope $end
$enddefinitions $end
#0
0!
1"
0#
b00 $
b0000 %
b0000 &
b00000000 '
U(
0)
1*
0+
b00 ,
b0000 -
b0000 .
b00000000 /
U0
b00000000 1
b00 2
b0000 3
b0000 4
b00000000 5
#5000000
1!
0(
1)
00
#10000000
0!
0"
0)
0*
#15000000
1!
1#
b0011 %
b0100 &
1)
1+
b0011 -
b0100 .
b0011 3
b0100 4
b00001100 5
#20000000
0!
0)
#25000000
1!
0#
b00001100 '
1(
1)
0+
b00001100 /
10
b00001100 1
#30000000
0!
0)
#35000000
1!
1)
#40000000
0!
0)
#45000000
1!
1)
#50000000
0!
0)
#55000000
1!
1#
b01 $
b0101 %
b0011 &
b00000000 '
0(
1)
1+
b01 ,
b0101 -
b0011 .
b00000000 /
00
b00000000 1
b01 2
b0101 3
b0011 4
b00001000 5
#60000000
0!
0)
#65000000
1!
0#
b00001000 '
1(
1)
0+
b00001000 /
10
b00001000 1
#70000000
0!
0)
#75000000
1!
1)
#80000000
0!
0)
#85000000
1!
1)
#90000000
0!
0)
#95000000
1!
1#
b10 $
b1010 %
b00000000 '
0(
1)
1+
b10 ,
b1010 -
b00000000 /
00
b00000000 1
b10 2
b1010 3
b00001010 5
#100000000
0!
0)
#105000000
1!
0#
b00001010 '
1(
1)
0+
b00001010 /
10
b00001010 1
#110000000
0!
0)
#115000000
1!
1)
#120000000
0!
0)
#125000000
1!
1)
#130000000
0!
0)
#135000000
1!
b1111 %
b0000 &
1)
b1111 -
b0000 .
#140000000
0!
0)
#145000000
1!
1)
#150000000
0!
0)
#155000000
1!
1)
#160000000
0!
0)
#165000000
1!
1)
#170000000
0!
0)
#175000000
1!
1#
b00 $
b1111 &
b00000000 '
0(
1)
1+
b00 ,
b1111 .
b00000000 /
00
b00000000 1
b00 2
b1111 3
b1111 4
b11100001 5
#180000000
0!
0)
#185000000
1!
0#
b11100001 '
1(
1)
0+
b11100001 /
10
b11100001 1
