projetv1/projet.srcs/sources_1/imports/ual/ual.vhd
library IEEE;
use IEEE.STD_LOGIC_1164.ALL;
use IEEE.NUMERIC_STD.ALL;

entity UAL is
    Port (
        A        : in  STD_LOGIC_VECTOR(3 downto 0);
        B        : in  STD_LOGIC_VECTOR(3 downto 0);
        SEL_FCT  : in  STD_LOGIC_VECTOR(3 downto 0);
        SEL_ROUTE: in  STD_LOGIC_VECTOR(3 downto 0);
        SEL_OUT  : in  STD_LOGIC_VECTOR(1 downto 0);
        SR_IN_L  : in  STD_LOGIC;
        SR_IN_R  : in  STD_LOGIC;
        S        : out STD_LOGIC_VECTOR(7 downto 0);
        SR_OUT_L : out STD_LOGIC;
        SR_OUT_R : out STD_LOGIC
    );
end UAL;

architecture Behavioral of UAL is
begin
    process(A, B, SEL_FCT, SEL_ROUTE, SEL_OUT, SR_IN_L, SR_IN_R)
        variable a_signed : signed(3 downto 0);
        variable b_signed : signed(3 downto 0);
        variable a_unsigned : unsigned(3 downto 0);
        variable b_unsigned : unsigned(3 downto 0);
    begin
        -- Initialisation par défaut pour éviter les verrous (latches)
        S <= (others => '0');
        SR_OUT_L <= '0';
        SR_OUT_R <= '0';

        -- Conversion pour les opérations arithmétiques signées
        a_signed := signed(A);
        b_signed := signed(B);
        a_unsigned := unsigned(A);
        b_unsigned := unsigned(B);

        case SEL_FCT is
            when "0000" => -- nop [cite: 169-174]
                S <= (others => '0');

            when "0001" => -- S = A [cite: 175-179]
                S <= std_logic_vector(resize(a_signed, 8));

            when "0010" => -- S = not A [cite: 180-185]
                S <= std_logic_vector(resize(not a_unsigned, 8));

            when "0011" => -- S = B [cite: 186-191]
                S <= std_logic_vector(resize(b_signed, 8));

            when "0100" => -- S = not B [cite: 192-196]
                S <= std_logic_vector(resize(not b_unsigned, 8));

            when "0101" => -- S = A and B [cite: 197-202]
                S <= std_logic_vector(resize(a_unsigned and b_unsigned, 8));

            when "0110" => -- S = A or B [cite: 203-208]
                S <= std_logic_vector(resize(a_unsigned or b_unsigned, 8));

            when "0111" => -- S = A xor B [cite: 209-213]
                S <= std_logic_vector(resize(a_unsigned xor b_unsigned, 8));

            when "1000" => -- S = A + B avec retenue d'entrée [cite: 214-218]
                if SR_IN_R = '1' then
                    S <= std_logic_vector(resize(a_signed + b_signed + 1, 8));
                else
                    S <= std_logic_vector(resize(a_signed + b_signed, 8));
                end if;

            when "1001" => -- S = A + B sans retenue [cite: 219-223]
                S <= std_logic_vector(resize(a_signed + b_signed, 8));

            when "1010" => -- S = A - B [cite: 224-228]
                S <= std_logic_vector(resize(a_signed - b_signed, 8));

            when "1011" => -- S = A * B [cite: 229-233]
                -- La multiplication de deux nombres de 4 bits donne naturellement un résultat sur 8 bits
                S <= std_logic_vector(a_signed * b_signed);

            when "1100" => -- Décalage droite A sur 4 bits [cite: 234-239]
                S(3) <= SR_IN_L;
                S(2 downto 0) <= A(3 downto 1);
                SR_OUT_R <= A(0);

            when "1101" => -- Décalage gauche A sur 4 bits [cite: 240-245]
                S(3 downto 1) <= A(2 downto 0);
                S(0) <= SR_IN_R;
                SR_OUT_L <= A(3);

            when "1110" => -- Décalage droite B sur 4 bits [cite: 246-250]
                S(3) <= SR_IN_L;
                S(2 downto 0) <= B(3 downto 1);
                SR_OUT_R <= B(0);

            when "1111" => -- Décalage gauche B sur 4 bits [cite: 251-255]
                S(3 downto 1) <= B(2 downto 0);
                S(0) <= SR_IN_R;
                SR_OUT_L <= B(3);

            when others =>
                S <= (others => '0');
        end case;
    end process;
end Behavioral;

ual/buffer_with_route.vhd
library IEEE;
use IEEE.STD_LOGIC_1164.ALL;
use IEEE.NUMERIC_STD.ALL;

-- Buffer with route selection: can be loaded from input or from output (feedback)
-- sel_route controls which source is written on rising_edge(clk)
-- sel_route = "00": load from input_data (e.g., A_IN or B_IN)
-- sel_route = "01": load from UAL output S
-- sel_route = "10": hold current value
-- sel_route = "11": clear
entity buffer_with_route is
    generic (
        WIDTH : positive := 8
    );
    Port (
        clk         : in  STD_LOGIC;
        reset       : in  STD_LOGIC;
        input_data  : in  STD_LOGIC_VECTOR(WIDTH-1 downto 0);
        ual_output  : in  STD_LOGIC_VECTOR(WIDTH-1 downto 0);
        sel_route   : in  STD_LOGIC_VECTOR(1 downto 0);
        buffer_out  : out STD_LOGIC_VECTOR(WIDTH-1 downto 0)
    );
end buffer_with_route;

architecture Behavioral of buffer_with_route is
    signal buf : STD_LOGIC_VECTOR(WIDTH-1 downto 0) := (others => '0');
begin
    process(clk)
    begin
        if rising_edge(clk) then
            if reset = '1' then
                buf <= (others => '0');
            else
                case sel_route is
                    when "00" =>   -- Load from input_data
                        buf <= input_data;
                    when "01" =>   -- Load from UAL output
                        buf <= ual_output;
                    when "10" =>   -- Hold
                        buf <= buf;
                    when "11" =>   -- Clear
                        buf <= (others => '0');
                    when others =>
                        buf <= (others => '0');
                end case;
            end if;
        end if;
    end process;

    buffer_out <= buf;

end Behavioral;

ual/register.vhd
library IEEE;
use IEEE.STD_LOGIC_1164.ALL;
use IEEE.NUMERIC_STD.ALL;

-- Generic synchronous register: memorizes input on clock rising edge if enabled
entity register_sync is
    generic (
        WIDTH : positive := 8  -- Width of data
    );
    Port (
        clk    : in  STD_LOGIC;
        reset  : in  STD_LOGIC;
        enable : in  STD_LOGIC;
        data_in : in  STD_LOGIC_VECTOR(WIDTH-1 downto 0);
        data_out: out STD_LOGIC_VECTOR(WIDTH-1 downto 0)
    );
end register_sync;

architecture Behavioral of register_sync is
    signal reg : STD_LOGIC_VECTOR(WIDTH-1 downto 0) := (others => '0');
begin
    process(clk)
    begin
        if rising_edge(clk) then
            if reset = '1' then
                reg <= (others => '0');
            elsif enable = '1' then
                reg <= data_in;
            end if;
        end if;
    end process;

    data_out <= reg;

end Behavioral;

instruction_memory.vhd
library IEEE;
use IEEE.STD_LOGIC_1164.ALL;
use IEEE.NUMERIC_STD.ALL;

entity instruction_memory is
    Port (
        clk          : in  STD_LOGIC;
        reset        : in  STD_LOGIC;
        instr_out    : out STD_LOGIC_VECTOR(9 downto 0);  -- 10-bit instruction
        pc_out       : out STD_LOGIC_VECTOR(6 downto 0)   -- Program counter (0-127)
    );
end instruction_memory;

architecture Behavioral of instruction_memory is
    type rom_type is array (0 to 127) of STD_LOGIC_VECTOR(9 downto 0);
    
    signal rom : rom_type := (
        0 => "0000001000", -- NOP, Load A_IN to Buf_A, Hold Buf_B
        1 => "0001011000", -- S=A, Load S to Buf_A & Cache_1
        
        -- Start LFSR loop
        2 => "1100100100", -- SRA, Hold Buf_A, Load Buf_B
        3 => "0111100100", -- A XOR B, Load Buf_B
        4 => "1110100100", -- SRB, Load Buf_B
        5 => "1110100100", -- SRB, Load Buf_B
        6 => "1111100100", -- SLB, Load Buf_B
        7 => "1111100100", -- SLB, Load Buf_B
        8 => "1111100100", -- SLB, Load Buf_B
        9 => "1110100100", -- SRB, Load Buf_B
        10=> "1110100100", -- SRB, Load Buf_B
        11=> "1110100100", -- SRB, Load Buf_B
        12=> "1101011000", -- SLA, Load Buf_A & Cache_1
        13=> "0110011000", -- A OR B, Load Buf_A & Cache_1
        
        others => "0000000000"
    );
    
    signal pc : unsigned(6 downto 0) := (others => '0');
    
begin
    
    process(clk)
    begin
        if rising_edge(clk) then
            if reset = '1' then
                pc <= (others => '0');
            else
                if pc = 13 then
                    pc <= to_unsigned(2, 7); -- Loop back
                else
                    pc <= pc + 1;
                end if;
            end if;
        end if;
    end process;
    
    instr_out <= rom(to_integer(pc));
    pc_out <= std_logic_vector(pc);
    
end Behavioral;

vhdl2_ual/vhdl2_ual.srcs/sources_1/imports/ual/memory_controller.vhd
library IEEE;
use IEEE.STD_LOGIC_1164.ALL;
use IEEE.NUMERIC_STD.ALL;

-- Memory Controller: orchestrates all buffers, caches, and registers
-- Connects instruction memory -> instruction decoder -> UAL control
entity memory_controller is
    Port (
        clk         : in  STD_LOGIC;
        reset       : in  STD_LOGIC;
        
        -- External inputs
        A_IN        : in  STD_LOGIC_VECTOR(3 downto 0);  -- 4-bit input A
        B_IN        : in  STD_LOGIC_VECTOR(3 downto 0);  -- 4-bit input B
        SR_IN_L     : in  STD_LOGIC;                     -- Left shift input
        SR_IN_R     : in  STD_LOGIC;                     -- Right shift input
        
        -- From UAL
        S_from_ual  : in  STD_LOGIC_VECTOR(7 downto 0);  -- UAL result
        SR_OUT_L    : in  STD_LOGIC;                      -- UAL shift output left
        SR_OUT_R    : in  STD_LOGIC;                      -- UAL shift output right
        
        -- Control signals to UAL (from instruction decoder)
        A_to_ual    : out STD_LOGIC_VECTOR(3 downto 0);
        B_to_ual    : out STD_LOGIC_VECTOR(3 downto 0);
        SEL_FCT     : out STD_LOGIC_VECTOR(3 downto 0);
        SEL_ROUTE   : out STD_LOGIC_VECTOR(3 downto 0);  -- No storage, used immediately
        SEL_OUT     : out STD_LOGIC_VECTOR(1 downto 0);
        
        -- Output data (cache outputs)
        CACHE_1_OUT : out STD_LOGIC_VECTOR(7 downto 0);
        CACHE_2_OUT : out STD_LOGIC_VECTOR(7 downto 0);
        
        -- Program counter visibility
        PC_OUT      : out STD_LOGIC_VECTOR(6 downto 0)
    );
end memory_controller;

architecture Behavioral of memory_controller is
    
    -- Internal signals
    signal instr            : STD_LOGIC_VECTOR(9 downto 0);
    signal sel_fct_instr    : STD_LOGIC_VECTOR(3 downto 0);
    signal sel_route_instr  : STD_LOGIC_VECTOR(3 downto 0);
    signal sel_out_instr    : STD_LOGIC_VECTOR(1 downto 0);
    
    signal buffer_a_out     : STD_LOGIC_VECTOR(3 downto 0);
    signal buffer_b_out     : STD_LOGIC_VECTOR(3 downto 0);
    signal cache_1_buf      : STD_LOGIC_VECTOR(7 downto 0);
    signal cache_2_buf      : STD_LOGIC_VECTOR(7 downto 0);
    
    signal mem_sel_fct      : STD_LOGIC_VECTOR(3 downto 0);
    signal mem_sel_out      : STD_LOGIC_VECTOR(1 downto 0);
    signal mem_sr_in_l      : STD_LOGIC;
    signal mem_sr_in_r      : STD_LOGIC;
    
    -- Route selection decoding (which buffer/cache to update)
    signal route_buf_a      : STD_LOGIC_VECTOR(1 downto 0);
    signal route_buf_b      : STD_LOGIC_VECTOR(1 downto 0);
    signal route_cache_1    : STD_LOGIC_VECTOR(1 downto 0);
    signal route_cache_2    : STD_LOGIC_VECTOR(1 downto 0);
    
begin
    
    -- ========================================
    -- 1. Instruction Memory (ROM with auto PC)
    -- ========================================
    instr_mem: entity work.instruction_memory
        port map (
            clk => clk,
            reset => reset,
            instr_out => instr,
            pc_out => PC_OUT
        );
    
    -- Decode instruction: [SEL_FCT(4)][SEL_ROUTE(4)][SEL_OUT(2)]
    sel_fct_instr   <= instr(9 downto 6);
    sel_route_instr <= instr(5 downto 2);
    sel_out_instr   <= instr(1 downto 0);
    
    -- ========================================
    -- 2. Synchronous Registers (always updated)
    -- ========================================
    
    -- MEM_SEL_FCT: stores selected function
    reg_sel_fct: entity work.register_sync
        generic map (WIDTH => 4)
        port map (
            clk => clk,
            reset => reset,
            enable => '1',
            data_in => sel_fct_instr,
            data_out => mem_sel_fct
        );
    
    -- MEM_SEL_OUT: stores output selection
    reg_sel_out: entity work.register_sync
        generic map (WIDTH => 2)
        port map (
            clk => clk,
            reset => reset,
            enable => '1',
            data_in => sel_out_instr,
            data_out => mem_sel_out
        );
    
    -- MEM_SR_IN_L: stores left shift input
    reg_sr_in_l: entity work.register_sync
        generic map (WIDTH => 1)
        port map (
            clk => clk,
            reset => reset,
            enable => '1',
            data_in(0) => SR_IN_L,
            data_out(0) => mem_sr_in_l
        );
    
    -- MEM_SR_IN_R: stores right shift input
    reg_sr_in_r: entity work.register_sync
        generic map (WIDTH => 1)
        port map (
            clk => clk,
            reset => reset,
            enable => '1',
            data_in(0) => SR_IN_R,
            data_out(0) => mem_sr_in_r
        );
    
    -- ========================================
    -- 3. Decode SEL_ROUTE to individual signals
    -- ========================================
    -- sel_route_instr format: [2 bits for buf_a][2 bits for buf_b][2 bits for cache_1][2 bits for cache_2]
    -- Actually, let's keep it simple: each buffer can have its own route code
    -- For now: treat sel_route_instr as follows:
    --   bits[3:2] -> Buffer_A, bits[1:0] -> Buffer_B
    -- Or interpret all 4 bits for multiplexed select
    
    -- Simple approach: bits [3:2] control what loads (00=input, 01=from S, 10=hold, 11=clear)
    route_buf_a <= sel_route_instr(3 downto 2);
    route_buf_b <= sel_route_instr(1 downto 0);
    -- For caches, we'll use different interpretations or duplicate logic
    route_cache_1 <= sel_route_instr(3 downto 2);
    route_cache_2 <= sel_route_instr(1 downto 0);
    
    -- ========================================
    -- 4. Buffers and Caches
    -- ========================================
    
    -- Buffer_A: stores A_IN or can load from UAL output
    buf_a: entity work.buffer_with_route
        generic map (WIDTH => 4)
        port map (
            clk => clk,
            reset => reset,
            input_data => A_IN,
            ual_output => S_from_ual(3 downto 0),  -- Lower 4 bits
            sel_route => route_buf_a,
            buffer_out => buffer_a_out
        );
    
    -- Buffer_B: stores B_IN or can load from UAL output
    buf_b: entity work.buffer_with_route
        generic map (WIDTH => 4)
        port map (
            clk => clk,
            reset => reset,
            input_data => B_IN,
            ual_output => S_from_ual(3 downto 0),  -- Lower 4 bits
            sel_route => route_buf_b,
            buffer_out => buffer_b_out
        );
    
    -- Cache_1: stores result from UAL (8 bits)
    cache_1: entity work.buffer_with_route
        generic map (WIDTH => 8)
        port map (
            clk => clk,
            reset => reset,
            input_data => (others => '0'),  -- Not used for cache
            ual_output => S_from_ual,
            sel_route => route_cache_1,
            buffer_out => cache_1_buf
        );
    
    -- Cache_2: stores result from UAL (8 bits)
    cache_2: entity work.buffer_with_route
        generic map (WIDTH => 8)
        port map (
            clk => clk,
            reset => reset,
            input_data => (others => '0'),  -- Not used for cache
            ual_output => S_from_ual,
            sel_route => route_cache_2,
            buffer_out => cache_2_buf
        );
    
    -- ========================================
    -- 5. Output assignments
    -- ========================================
    
    -- Data to UAL (from buffers)
    A_to_ual <= buffer_a_out;
    B_to_ual <= buffer_b_out;
    
    -- Control signals to UAL (from stored registers)
    SEL_FCT <= mem_sel_fct;
    SEL_ROUTE <= sel_route_instr;  -- SEL_ROUTE not stored, used immediately
    SEL_OUT <= mem_sel_out;
    
    -- Cache outputs
    CACHE_1_OUT <= cache_1_buf;
    CACHE_2_OUT <= cache_2_buf;
    
end Behavioral;

ual/memory_system_tb.vhd
library IEEE;
use IEEE.STD_LOGIC_1164.ALL;
use IEEE.NUMERIC_STD.ALL;

entity memory_system_tb is
end memory_system_tb;

architecture behavior of memory_system_tb is

    -- Components
    component memory_controller
        Port (
            clk         : in  STD_LOGIC;
            reset       : in  STD_LOGIC;
            A_IN        : in  STD_LOGIC_VECTOR(3 downto 0);
            B_IN        : in  STD_LOGIC_VECTOR(3 downto 0);
            SR_IN_L     : in  STD_LOGIC;
            SR_IN_R     : in  STD_LOGIC;
            S_from_ual  : in  STD_LOGIC_VECTOR(7 downto 0);
            SR_OUT_L    : in  STD_LOGIC;
            SR_OUT_R    : in  STD_LOGIC;
            A_to_ual    : out STD_LOGIC_VECTOR(3 downto 0);
            B_to_ual    : out STD_LOGIC_VECTOR(3 downto 0);
            SEL_FCT     : out STD_LOGIC_VECTOR(3 downto 0);
            SEL_ROUTE   : out STD_LOGIC_VECTOR(3 downto 0);
            SEL_OUT     : out STD_LOGIC_VECTOR(1 downto 0);
            CACHE_1_OUT : out STD_LOGIC_VECTOR(7 downto 0);
            CACHE_2_OUT : out STD_LOGIC_VECTOR(7 downto 0);
            PC_OUT      : out STD_LOGIC_VECTOR(6 downto 0)
        );
    end component;

    component UAL
        Port (
            A        : in  STD_LOGIC_VECTOR(3 downto 0);
            B        : in  STD_LOGIC_VECTOR(3 downto 0);
            SEL_FCT  : in  STD_LOGIC_VECTOR(3 downto 0);
            SEL_ROUTE: in  STD_LOGIC_VECTOR(3 downto 0);
            SEL_OUT  : in  STD_LOGIC_VECTOR(1 downto 0);
            SR_IN_L  : in  STD_LOGIC;
            SR_IN_R  : in  STD_LOGIC;
            S        : out STD_LOGIC_VECTOR(7 downto 0);
            SR_OUT_L : out STD_LOGIC;
            SR_OUT_R : out STD_LOGIC
        );
    end component;

    -- Signals
    signal clk              : STD_LOGIC := '0';
    signal reset            : STD_LOGIC := '1';
    signal A_IN_tb          : STD_LOGIC_VECTOR(3 downto 0) := "0011";
    signal B_IN_tb          : STD_LOGIC_VECTOR(3 downto 0) := "0100";
    signal SR_IN_L_tb       : STD_LOGIC := '0';
    signal SR_IN_R_tb       : STD_LOGIC := '0';
    
    signal A_to_ual_sig     : STD_LOGIC_VECTOR(3 downto 0);
    signal B_to_ual_sig     : STD_LOGIC_VECTOR(3 downto 0);
    signal SEL_FCT_sig      : STD_LOGIC_VECTOR(3 downto 0);
    signal SEL_ROUTE_sig    : STD_LOGIC_VECTOR(3 downto 0);
    signal SEL_OUT_sig      : STD_LOGIC_VECTOR(1 downto 0);
    signal S_from_ual_sig   : STD_LOGIC_VECTOR(7 downto 0);
    signal SR_OUT_L_sig     : STD_LOGIC;
    signal SR_OUT_R_sig     : STD_LOGIC;
    signal CACHE_1_sig      : STD_LOGIC_VECTOR(7 downto 0);
    signal CACHE_2_sig      : STD_LOGIC_VECTOR(7 downto 0);
    signal PC_sig           : STD_LOGIC_VECTOR(6 downto 0);

begin

    -- Instantiate memory controller
    mem_ctrl: memory_controller
        port map (
            clk => clk,
            reset => reset,
            A_IN => A_IN_tb,
            B_IN => B_IN_tb,
            SR_IN_L => SR_IN_L_tb,
            SR_IN_R => SR_IN_R_tb,
            S_from_ual => S_from_ual_sig,
            SR_OUT_L => SR_OUT_L_sig,
            SR_OUT_R => SR_OUT_R_sig,
            A_to_ual => A_to_ual_sig,
            B_to_ual => B_to_ual_sig,
            SEL_FCT => SEL_FCT_sig,
            SEL_ROUTE => SEL_ROUTE_sig,
            SEL_OUT => SEL_OUT_sig,
            CACHE_1_OUT => CACHE_1_sig,
            CACHE_2_OUT => CACHE_2_sig,
            PC_OUT => PC_sig
        );

    -- Instantiate UAL
    ual_inst: UAL
        port map (
            A => A_to_ual_sig,
            B => B_to_ual_sig,
            SEL_FCT => SEL_FCT_sig,
            SEL_ROUTE => SEL_ROUTE_sig,
            SEL_OUT => SEL_OUT_sig,
            SR_IN_L => SR_IN_L_tb,
            SR_IN_R => SR_IN_R_tb,
            S => S_from_ual_sig,
            SR_OUT_L => SR_OUT_L_sig,
            SR_OUT_R => SR_OUT_R_sig
        );

    -- Clock generation
    clk_proc: process
    begin
        while True loop
            clk <= '0';
            wait for 5 ns;
            clk <= '1';
            wait for 5 ns;
        end loop;
        wait;
    end process clk_proc;

    -- Stimulus process
    stim_proc: process
    begin
        -- Reset pulse
        reset <= '1';
        wait for 10 ns;
        reset <= '0';
        
        -- Apply some test vectors
        A_IN_tb <= "0011"; -- 3
        B_IN_tb <= "0100"; -- 4
        wait for 20 ns;
        
        A_IN_tb <= "1100";
        B_IN_tb <= "1010";
        wait for 20 ns;
        
        A_IN_tb <= "0111";
        B_IN_tb <= "0010";
        wait for 20 ns;
        
        wait;
    end process;

end behavior;

ual/memory_system.vcd
$date
  Mon May  4 10:10:34 2026
$end
$version
  GHDL v0
$end
$timescale
  1 fs
$end
$scope module standard $end
$upscope $end
$scope module textio $end
$upscope $end
$scope module std_logic_1164 $end
$upscope $end
$scope module numeric_std $end
$upscope $end
$scope module memory_system_tb $end
$var reg 1 ! clk $end
$var reg 1 " reset $end
$var reg 4 # a_in_tb[3:0] $end
$var reg 4 $ b_in_tb[3:0] $end
$var reg 1 % sr_in_l_tb $end
$var reg 1 & sr_in_r_tb $end
$var reg 4 ' a_to_ual_sig[3:0] $end
$var reg 4 ( b_to_ual_sig[3:0] $end
$var reg 4 ) sel_fct_sig[3:0] $end
$var reg 4 * sel_route_sig[3:0] $end
$var reg 2 + sel_out_sig[1:0] $end
$var reg 8 , s_from_ual_sig[7:0] $end
$var reg 1 - sr_out_l_sig $end
$var reg 1 . sr_out_r_sig $end
$var reg 8 / cache_1_sig[7:0] $end
$var reg 8 0 cache_2_sig[7:0] $end
$var reg 7 1 pc_sig[6:0] $end
$scope module mem_ctrl $end
$var reg 1 2 clk $end
$var reg 1 3 reset $end
$var reg 4 4 a_in[3:0] $end
$var reg 4 5 b_in[3:0] $end
$var reg 1 6 sr_in_l $end
$var reg 1 7 sr_in_r $end
$var reg 8 8 s_from_ual[7:0] $end
$var reg 1 9 sr_out_l $end
$var reg 1 : sr_out_r $end
$var reg 4 ; a_to_ual[3:0] $end
$var reg 4 < b_to_ual[3:0] $end
$var reg 4 = sel_fct[3:0] $end
$var reg 4 > sel_route[3:0] $end
$var reg 2 ? sel_out[1:0] $end
$var reg 8 @ cache_1_out[7:0] $end
$var reg 8 A cache_2_out[7:0] $end
$var reg 7 B pc_out[6:0] $end
$var reg 10 C instr[9:0] $end
$var reg 4 D sel_fct_instr[3:0] $end
$var reg 4 E sel_route_instr[3:0] $end
$var reg 2 F sel_out_instr[1:0] $end
$var reg 4 G buffer_a_out[3:0] $end
$var reg 4 H buffer_b_out[3:0] $end
$var reg 8 I cache_1_buf[7:0] $end
$var reg 8 J cache_2_buf[7:0] $end
$var reg 4 K mem_sel_fct[3:0] $end
$var reg 2 L mem_sel_out[1:0] $end
$var reg 1 M mem_sr_in_l $end
$var reg 1 N mem_sr_in_r $end
$var reg 2 O route_buf_a[1:0] $end
$var reg 2 P route_buf_b[1:0] $end
$var reg 2 Q route_cache_1[1:0] $end
$var reg 2 R route_cache_2[1:0] $end
$scope module instr_mem $end
$var reg 1 S clk $end
$var reg 1 T reset $end
$var reg 10 U instr_out[9:0] $end
$var reg 7 V pc_out[6:0] $end
$comment rom is not handled $end
$var reg 7 W pc[6:0] $end
$upscope $end
$scope module reg_sel_fct $end
$var reg 1 X clk $end
$var reg 1 Y reset $end
$var reg 1 Z enable $end
$var reg 4 [ data_in[3:0] $end
$var reg 4 \ data_out[3:0] $end
$var reg 4 ] reg[3:0] $end
$upscope $end
$scope module reg_sel_out $end
$var reg 1 ^ clk $end
$var reg 1 _ reset $end
$var reg 1 ` enable $end
$var reg 2 a data_in[1:0] $end
$var reg 2 b data_out[1:0] $end
$var reg 2 c reg[1:0] $end
$upscope $end
$scope module reg_sr_in_l $end
$var reg 1 d clk $end
$var reg 1 e reset $end
$var reg 1 f enable $end
$var reg 1 g data_in[0:0] $end
$var reg 1 h data_out[0:0] $end
$var reg 1 i reg[0:0] $end
$upscope $end
$scope module reg_sr_in_r $end
$var reg 1 j clk $end
$var reg 1 k reset $end
$var reg 1 l enable $end
$var reg 1 m data_in[0:0] $end
$var reg 1 n data_out[0:0] $end
$var reg 1 o reg[0:0] $end
$upscope $end
$scope module buf_a $end
$var reg 1 p clk $end
$var reg 1 q reset $end
$var reg 4 r input_data[3:0] $end
$var reg 4 s ual_output[3:0] $end
$var reg 2 t sel_route[1:0] $end
$var reg 4 u buffer_out[3:0] $end
$var reg 4 v buf[3:0] $end
$upscope $end
$scope module buf_b $end
$var reg 1 w clk $end
$var reg 1 x reset $end
$var reg 4 y input_data[3:0] $end
$var reg 4 z ual_output[3:0] $end
$var reg 2 { sel_route[1:0] $end
$var reg 4 | buffer_out[3:0] $end
$var reg 4 } buf[3:0] $end
$upscope $end
$scope module cache_1 $end
$var reg 1 !" clk $end
$var reg 1 "" reset $end
$var reg 8 #" input_data[7:0] $end
$var reg 8 $" ual_output[7:0] $end
$var reg 2 %" sel_route[1:0] $end
$var reg 8 &" buffer_out[7:0] $end
$var reg 8 '" buf[7:0] $end
$upscope $end
$scope module cache_2 $end
$var reg 1 (" clk $end
$var reg 1 )" reset $end
$var reg 8 *" input_data[7:0] $end
$var reg 8 +" ual_output[7:0] $end
$var reg 2 ," sel_route[1:0] $end
$var reg 8 -" buffer_out[7:0] $end
$var reg 8 ." buf[7:0] $end
$upscope $end
$upscope $end
$scope module ual_inst $end
$var reg 4 /" a[3:0] $end
$var reg 4 0" b[3:0] $end
$var reg 4 1" sel_fct[3:0] $end
$var reg 4 2" sel_route[3:0] $end
$var reg 2 3" sel_out[1:0] $end
$var reg 1 4" sr_in_l $end
$var reg 1 5" sr_in_r $end
$var reg 8 6" s[7:0] $end
$var reg 1 7" sr_out_l $end
$var reg 1 8" sr_out_r $end
$upscope $end
$upscope $end
$enddefinitions $end
#0
0!
1"
b0011 #
b0100 $
0%
0&
b0000 '
b0000 (
b0000 )
b0000 *
b00 +
b00000000 ,
0-
0.
b00000000 /
b00000000 0
b0000000 1
02
13
b0011 4
b0100 5
06
07
b00000000 8
09
0:
b0000 ;
b0000 <
b0000 =
b0000 >
b00 ?
b00000000 @
b00000000 A
b0000000 B
b0000000000 C
b0000 D
b0000 E
b00 F
b0000 G
b0000 H
b00000000 I
b00000000 J
b0000 K
b00 L
0M
0N
b00 O
b00 P
b00 Q
b00 R
0S
1T
b0000000000 U
b0000000 V
b0000000 W
0X
1Y
1Z
b0000 [
b0000 \
b0000 ]
0^
1_
1`
b00 a
b00 b
b00 c
0d
1e
1f
b0 g
b0 h
b0 i
0j
1k
1l
b0 m
b0 n
b0 o
0p
1q
b0011 r
b0000 s
b00 t
b0000 u
b0000 v
0w
1x
b0100 y
b0000 z
b00 {
b0000 |
b0000 }
0!"
1""
b00000000 #"
b00000000 $"
b00 %"
b00000000 &"
b00000000 '"
0("
1)"
b00000000 *"
b00000000 +"
b00 ,"
b00000000 -"
b00000000 ."
b0000 /"
b0000 0"
b0000 1"
b0000 2"
b00 3"
04"
05"
b00000000 6"
07"
08"
#5000000
1!
12
1S
1X
1^
1d
1j
1p
1w
1!"
1("
#10000000
0!
0"
02
03
0S
0T
0X
0Y
0^
0_
0d
0e
0j
0k
0p
0q
0w
0x
0!"
0""
0("
0)"
#15000000
1!
b0011 '
b0100 (
b0000001 1
12
b0011 ;
b0100 <
b0000001 B
b1001000000 C
b1001 D
b0011 G
b0100 H
1S
b1001000000 U
b0000001 V
b0000001 W
1X
b1001 [
1^
1d
1j
1p
b0011 u
b0011 v
1w
b0100 |
b0100 }
1!"
1("
b0011 /"
b0100 0"
#20000000
0!
02
0S
0X
0^
0d
0j
0p
0w
0!"
0("
#25000000
1!
b1001 )
b0001 *
b00000111 ,
b0000010 1
12
b00000111 8
b1001 =
b0001 >
b0000010 B
b0101000101 C
b0101 D
b0001 E
b01 F
b1001 K
b01 P
b01 R
1S
b0101000101 U
b0000010 V
b0000010 W
1X
b0101 [
b1001 \
b1001 ]
1^
b01 a
1d
1j
1p
b0111 s
1w
b0111 z
b01 {
1!"
b00000111 $"
1("
b00000111 +"
b01 ,"
b1001 1"
b0001 2"
b00000111 6"
#30000000
0!
b1100 #
b1010 $
02
b1100 4
b1010 5
0S
0X
0^
0d
0j
0p
b1100 r
0w
b1010 y
0!"
0("
#35000000
1!
b1100 '
b0111 (
b0101 )
b0010 *
b01 +
b00000100 ,
b00000111 0
b0000011 1
12
b00000100 8
b1100 ;
b0111 <
b0101 =
b0010 >
b01 ?
b00000111 A
b0000011 B
b1010001010 C
b1010 D
b0010 E
b10 F
b1100 G
b0111 H
b00000111 J
b0101 K
b01 L
b10 P
b10 R
1S
b1010001010 U
b0000011 V
b0000011 W
1X
b1010 [
b0101 \
b0101 ]
1^
b10 a
b01 b
b01 c
1d
1j
1p
b0100 s
b1100 u
b1100 v
1w
b0100 z
b10 {
b0111 |
b0111 }
1!"
b00000100 $"
1("
b00000100 +"
b10 ,"
b00000111 -"
b00000111 ."
b1100 /"
b0111 0"
b0101 1"
b0010 2"
b01 3"
b00000100 6"
#40000000
0!
02
0S
0X
0^
0d
0j
0p
0w
0!"
0("
#45000000
1!
b1010 )
b0000 *
b10 +
b00000101 ,
b0000100 1
12
b00000101 8
b1010 =
b0000 >
b10 ?
b0000100 B
b0000000000 C
b0000 D
b0000 E
b00 F
b1010 K
b10 L
b00 P
b00 R
1S
b0000000000 U
b0000100 V
b0000100 W
1X
b0000 [
b1010 \
b1010 ]
1^
b00 a
b10 b
b10 c
1d
1j
1p
b0101 s
1w
b0101 z
b00 {
1!"
b00000101 $"
1("
b00000101 +"
b00 ,"
b1010 1"
b0000 2"
b10 3"
b00000101 6"
#50000000
0!
b0111 #
b0010 $
02
b0111 4
b0010 5
0S
0X
0^
0d
0j
0p
b0111 r
0w
b0010 y
0!"
0("
#55000000
1!
b0111 '
b0010 (
b0000 )
b00 +
b00000000 ,
b00000000 0
b0000101 1
12
b00000000 8
b0111 ;
b0010 <
b0000 =
b00 ?
b00000000 A
b0000101 B
b0111 G
b0010 H
b00000000 J
b0000 K
b00 L
1S
b0000101 V
b0000101 W
1X
b0000 \
b0000 ]
1^
b00 b
b00 c
1d
1j
1p
b0000 s
b0111 u
b0111 v
1w
b0000 z
b0010 |
b0010 }
1!"
b00000000 $"
1("
b00000000 +"
b00000000 -"
b00000000 ."
b0111 /"
b0010 0"
b0000 1"
b00 3"
b00000000 6"
#60000000
0!
02
0S
0X
0^
0d
0j
0p
0w
0!"
0("
#65000000
1!
b0000110 1
12
b0000110 B
1S
b0000110 V
b0000110 W
1X
1^
1d
1j
1p
1w
1!"
1("
#70000000
0!
02
0S
0X
0^
0d
0j
0p
0w
0!"
0("
#75000000
1!
b0000111 1
12
b0000111 B
1S
b0000111 V
b0000111 W
1X
1^
1d
1j
1p
1w
1!"
1("
#80000000
0!
02
0S
0X
0^
0d
0j
0p
0w
0!"
0("
#85000000
1!
b0001000 1
12
b0001000 B
1S
b0001000 V
b0001000 W
1X
1^
1d
1j
1p
1w
1!"
1("
#90000000
0!
02
0S
0X
0^
0d
0j
0p
0w
0!"
0("
#95000000
1!
b0001001 1
12
b0001001 B
1S
b0001001 V
b0001001 W
1X
1^
1d
1j
1p
1w
1!"
1("
