projetv1/projet.srcs/sources_1/imports/ual/ual_controller.vhd
library IEEE;
use IEEE.STD_LOGIC_1164.ALL;

entity UAL_Controller is
    Port (
        clk      : in  STD_LOGIC;
        reset    : in  STD_LOGIC;
        instr_in : in  STD_LOGIC_VECTOR(9 downto 0); -- [9:6]=SEL_FCT, [5:2]=SEL_ROUTE, [1:0]=SEL_OUT
        SEL_FCT  : out STD_LOGIC_VECTOR(3 downto 0);
        SEL_ROUTE: out STD_LOGIC_VECTOR(3 downto 0);
        SEL_OUT  : out STD_LOGIC_VECTOR(1 downto 0)
    );
end UAL_Controller;

architecture Behavioral of UAL_Controller is
begin
    process(clk)
    begin
        if rising_edge(clk) then
            if reset = '1' then
                SEL_FCT   <= (others => '0');
                SEL_ROUTE <= (others => '0');
                SEL_OUT   <= (others => '0');
            else
                SEL_FCT   <= instr_in(9 downto 6);
                SEL_ROUTE <= instr_in(5 downto 2);
                SEL_OUT   <= instr_in(1 downto 0);
            end if;
        end if;
    end process;
end Behavioral;

projetv1/projet.srcs/sources_1/imports/ual/ual.vhd
library IEEE;
use IEEE.STD_LOGIC_1164.ALL;
use IEEE.NUMERIC_STD.ALL;

entity UAL is
    Port (
        A        : in  STD_LOGIC_VECTOR(3 downto 0);
        B        : in  STD_LOGIC_VECTOR(3 downto 0);
        SEL_FCT  : in  STD_LOGIC_VECTOR(3 downto 0);
        SEL_ROUTE: in  STD_LOGIC_VECTOR(3 downto 0);
        SEL_OUT  : in  STD_LOGIC_VECTOR(1 downto 0);
        SR_IN_L  : in  STD_LOGIC;
        SR_IN_R  : in  STD_LOGIC;
        S        : out STD_LOGIC_VECTOR(7 downto 0);
        SR_OUT_L : out STD_LOGIC;
        SR_OUT_R : out STD_LOGIC
    );
end UAL;

architecture Behavioral of UAL is
begin
    process(A, B, SEL_FCT, SEL_ROUTE, SEL_OUT, SR_IN_L, SR_IN_R)
        variable a_signed : signed(3 downto 0);
        variable b_signed : signed(3 downto 0);
        variable a_unsigned : unsigned(3 downto 0);
        variable b_unsigned : unsigned(3 downto 0);
    begin
        -- Initialisation par défaut pour éviter les verrous (latches)
        S <= (others => '0');
        SR_OUT_L <= '0';
        SR_OUT_R <= '0';

        -- Conversion pour les opérations arithmétiques signées
        a_signed := signed(A);
        b_signed := signed(B);
        a_unsigned := unsigned(A);
        b_unsigned := unsigned(B);

        case SEL_FCT is
            when "0000" => -- nop [cite: 169-174]
                S <= (others => '0');

            when "0001" => -- S = A [cite: 175-179]
                S <= std_logic_vector(resize(a_signed, 8));

            when "0010" => -- S = not A [cite: 180-185]
                S <= std_logic_vector(resize(not a_unsigned, 8));

            when "0011" => -- S = B [cite: 186-191]
                S <= std_logic_vector(resize(b_signed, 8));

            when "0100" => -- S = not B [cite: 192-196]
                S <= std_logic_vector(resize(not b_unsigned, 8));

            when "0101" => -- S = A and B [cite: 197-202]
                S <= std_logic_vector(resize(a_unsigned and b_unsigned, 8));

            when "0110" => -- S = A or B [cite: 203-208]
                S <= std_logic_vector(resize(a_unsigned or b_unsigned, 8));

            when "0111" => -- S = A xor B [cite: 209-213]
                S <= std_logic_vector(resize(a_unsigned xor b_unsigned, 8));

            when "1000" => -- S = A + B avec retenue d'entrée [cite: 214-218]
                if SR_IN_R = '1' then
                    S <= std_logic_vector(resize(a_signed + b_signed + 1, 8));
                else
                    S <= std_logic_vector(resize(a_signed + b_signed, 8));
                end if;

            when "1001" => -- S = A + B sans retenue [cite: 219-223]
                S <= std_logic_vector(resize(a_signed + b_signed, 8));

            when "1010" => -- S = A - B [cite: 224-228]
                S <= std_logic_vector(resize(a_signed - b_signed, 8));

            when "1011" => -- S = A * B [cite: 229-233]
                -- La multiplication de deux nombres de 4 bits donne naturellement un résultat sur 8 bits
                S <= std_logic_vector(a_signed * b_signed);

            when "1100" => -- Décalage droite A sur 4 bits [cite: 234-239]
                S(3) <= SR_IN_L;
                S(2 downto 0) <= A(3 downto 1);
                SR_OUT_R <= A(0);

            when "1101" => -- Décalage gauche A sur 4 bits [cite: 240-245]
                S(3 downto 1) <= A(2 downto 0);
                S(0) <= SR_IN_R;
                SR_OUT_L <= A(3);

            when "1110" => -- Décalage droite B sur 4 bits [cite: 246-250]
                S(3) <= SR_IN_L;
                S(2 downto 0) <= B(3 downto 1);
                SR_OUT_R <= B(0);

            when "1111" => -- Décalage gauche B sur 4 bits [cite: 251-255]
                S(3 downto 1) <= B(2 downto 0);
                S(0) <= SR_IN_R;
                SR_OUT_L <= B(3);

            when others =>
                S <= (others => '0');
        end case;
    end process;
end Behavioral;

ual/ualtb.vhd
library IEEE;
use IEEE.STD_LOGIC_1164.ALL;
use IEEE.NUMERIC_STD.ALL;

entity UAL_tb is
-- Un testbench n'a jamais de ports d'entrée ou de sortie
end UAL_tb;

architecture behavior of UAL_tb is

    -- 1. Déclaration du composant à tester (ton UAL)
    component UAL
        Port (
            A        : in  STD_LOGIC_VECTOR(3 downto 0);
            B        : in  STD_LOGIC_VECTOR(3 downto 0);
            SEL_FCT  : in  STD_LOGIC_VECTOR(3 downto 0);
            SEL_ROUTE: in  STD_LOGIC_VECTOR(3 downto 0);
            SEL_OUT  : in  STD_LOGIC_VECTOR(1 downto 0);
            SR_IN_L  : in  STD_LOGIC;
            SR_IN_R  : in  STD_LOGIC;
            S        : out STD_LOGIC_VECTOR(7 downto 0);
            SR_OUT_L : out STD_LOGIC;
            SR_OUT_R : out STD_LOGIC
        );
    end component;

    -- 2. Création des signaux internes pour câbler le composant
    signal A_tb        : STD_LOGIC_VECTOR(3 downto 0) := "0000";
    signal B_tb        : STD_LOGIC_VECTOR(3 downto 0) := "0000";
    signal SEL_FCT_tb  : STD_LOGIC_VECTOR(3 downto 0) := "0000";
    signal SEL_ROUTE_tb: STD_LOGIC_VECTOR(3 downto 0) := "0000";
    signal SEL_OUT_tb  : STD_LOGIC_VECTOR(1 downto 0) := "00";
    signal instr_tb    : STD_LOGIC_VECTOR(9 downto 0) := (others => '0');
    signal clk_tb      : STD_LOGIC := '0';
    signal reset_tb    : STD_LOGIC := '1';
    signal SR_IN_L_tb  : STD_LOGIC := '0';
    signal SR_IN_R_tb  : STD_LOGIC := '0';
    signal S_tb        : STD_LOGIC_VECTOR(7 downto 0);
    signal SR_OUT_L_tb : STD_LOGIC;
    signal SR_OUT_R_tb : STD_LOGIC;

begin

    -- 3. Instanciation de l'UAL (on relie les signaux du testbench aux ports de l'UAL)
    uut: UAL PORT MAP (
        A => A_tb,
        B => B_tb,
        SEL_FCT => SEL_FCT_tb,
        SEL_ROUTE => SEL_ROUTE_tb,
        SEL_OUT => SEL_OUT_tb,
        SR_IN_L => SR_IN_L_tb,
        SR_IN_R => SR_IN_R_tb,
        S => S_tb,
        SR_OUT_L => SR_OUT_L_tb,
        SR_OUT_R => SR_OUT_R_tb
    );

    controller_inst: entity work.UAL_Controller
        port map (
            clk => clk_tb,
            reset => reset_tb,
            instr_in => instr_tb,
            SEL_FCT => SEL_FCT_tb,
            SEL_ROUTE => SEL_ROUTE_tb,
            SEL_OUT => SEL_OUT_tb
        );

    -- 4. Le processus de test (les stimulus)
    -- Clock generation
    clk_proc: process
    begin
        while True loop
            clk_tb <= '0';
            wait for 5 ns;
            clk_tb <= '1';
            wait for 5 ns;
        end loop;
        wait;
    end process clk_proc;

    -- Stimulus process (drives instruction vector, A/B and reset)
    stim_proc2: process
    begin
        -- Reset pulse
        reset_tb <= '1';
        wait for 12 ns;
        reset_tb <= '0';
        wait for 8 ns;

        -- Afin d'être sûr d'attendre le coup d'horloge pour le contrôleur
        -- chaque test assignera les entrées, puis attendra 20 ns pour lire et vérifier

        -- Test 0: NOP (0000)
        A_tb <= "0101";
        B_tb <= "0011";
        instr_tb <= "0000" & "0000" & "00";
        wait for 20 ns;
        assert (S_tb = "00000000") report "Echec Test 0: NOP" severity error;

        -- Test 1: S = A (0001)
        A_tb <= "0110"; -- 6
        B_tb <= "1001";
        instr_tb <= "0001" & "0000" & "00";
        wait for 20 ns;
        assert (S_tb = "00000110") report "Echec Test 1: S = A" severity error;

        -- Test 2: S = not A (0010)
        A_tb <= "0101"; 
        instr_tb <= "0010" & "0000" & "00";
        wait for 20 ns;
        assert (S_tb = "00001010") report "Echec Test 2: S = not A" severity error; -- not 0101 = 1010

        -- Test 3: S = B (0011)
        A_tb <= "0000";
        B_tb <= "1100"; -- -4 ou 12 (unsigned)
        instr_tb <= "0011" & "0000" & "00";
        wait for 20 ns;
        -- B est casté en signed 8 bits : 1100 sign-extended -> 11111100
        assert (S_tb = "11111100") report "Echec Test 3: S = B" severity error;

        -- Test 4: S = not B (0100)
        B_tb <= "0110"; 
        instr_tb <= "0100" & "0000" & "00";
        wait for 20 ns;
        assert (S_tb = "00001001") report "Echec Test 4: S = not B" severity error; -- not 0110 = 1001

        -- Test 5: S = A and B (0101)
        A_tb <= "1100";
        B_tb <= "1010";
        instr_tb <= "0101" & "0000" & "00";
        wait for 20 ns;
        assert (S_tb = "00001000") report "Echec Test 5: A and B" severity error;

        -- Test 6: S = A or B (0110)
        A_tb <= "1100";
        B_tb <= "1010";
        instr_tb <= "0110" & "0000" & "00";
        wait for 20 ns;
        assert (S_tb = "00001110") report "Echec Test 6: A or B" severity error;

        -- Test 7: S = A xor B (0111)
        A_tb <= "1100";
        B_tb <= "1010";
        instr_tb <= "0111" & "0000" & "00";
        wait for 20 ns;
        assert (S_tb = "00000110") report "Echec Test 7: A xor B" severity error;

        -- Test 8: S = A + B avec retenue d'entrée (1000)
        A_tb <= "0011"; -- 3
        B_tb <= "0010"; -- 2
        SR_IN_R_tb <= '1';
        instr_tb <= "1000" & "0000" & "00";
        wait for 20 ns;
        assert (S_tb = "00000110") report "Echec Test 8: A + B + 1" severity error; -- 3 + 2 + 1 = 6

        -- Test 9: S = A + B sans retenue (1001)
        A_tb <= "0010"; -- 2
        B_tb <= "0011"; -- 3
        SR_IN_R_tb <= '0';
        instr_tb <= "1001" & "0000" & "00";
        wait for 20 ns;
        assert (S_tb = "00000101") report "Echec Test 9: A + B" severity error; -- 2 + 3 = 5

        -- Test 10: S = A - B (1010)
        A_tb <= "0111"; -- 7
        B_tb <= "0010"; -- 2
        instr_tb <= "1010" & "0000" & "00";
        wait for 20 ns;
        assert (S_tb = "00000101") report "Echec Test 10: A - B" severity error; -- 7 - 2 = 5

        -- Test 11: S = A * B (1011)
        A_tb <= "0011"; -- 3
        B_tb <= "0010"; -- 2
        instr_tb <= "1011" & "0000" & "00";
        wait for 20 ns;
        assert (S_tb = "00000110") report "Echec Test 11: A * B" severity error; -- 3 * 2 = 6

        -- Test 12: Décalage droite A sur 4 bits (1100)
        A_tb <= "1010";
        SR_IN_L_tb <= '1';
        instr_tb <= "1100" & "0000" & "00";
        wait for 20 ns;
        -- S(3) <= SR_IN_L (1), S(2..0) <= A(3..1) (101) => 1101
        assert (S_tb(3 downto 0) = "1101" and SR_OUT_R_tb = '0') report "Echec Test 12: Déc Droite A" severity error;

        -- Test 13: Décalage gauche A sur 4 bits (1101)
        A_tb <= "1010";
        SR_IN_R_tb <= '1';
        instr_tb <= "1101" & "0000" & "00";
        wait for 20 ns;
        -- S(3..1) <= A(2..0) (010), S(0) <= SR_IN_R (1) => 0101
        assert (S_tb(3 downto 0) = "0101" and SR_OUT_L_tb = '1') report "Echec Test 13: Déc Gauche A" severity error;

        -- Test 14: Décalage droite B (1110)
        B_tb <= "0111";
        SR_IN_L_tb <= '0';
        instr_tb <= "1110" & "0000" & "00";
        wait for 20 ns;
        -- S(3) <= 0, S(2..0) <= B(3..1) (011) => 0011
        assert (S_tb(3 downto 0) = "0011" and SR_OUT_R_tb = '1') report "Echec Test 14: Déc Droite B" severity error;

        -- Test 15: Décalage gauche B (1111)
        B_tb <= "1101";
        SR_IN_R_tb <= '0';
        instr_tb <= "1111" & "0000" & "00";
        wait for 20 ns;
        -- S(3..1) <= B(2..0) (101), S(0) <= 0 => 1010
        assert (S_tb(3 downto 0) = "1010" and SR_OUT_L_tb = '1') report "Echec Test 15: Déc Gauche B" severity error;

        report "TESTS TERMINES AVEC SUCCES" severity note;
        wait;
    end process;

end behavior;

ual/ual_tb.vcd
$date
  Mon May  4 09:52:36 2026
$end
$version
  GHDL v0
$end
$timescale
  1 fs
$end
$scope module standard $end
$upscope $end
$scope module textio $end
$upscope $end
$scope module std_logic_1164 $end
$upscope $end
$scope module numeric_std $end
$upscope $end
$scope module ual_tb $end
$var reg 4 ! a_tb[3:0] $end
$var reg 4 " b_tb[3:0] $end
$var reg 4 # sel_fct_tb[3:0] $end
$var reg 4 $ sel_route_tb[3:0] $end
$var reg 2 % sel_out_tb[1:0] $end
$var reg 10 & instr_tb[9:0] $end
$var reg 1 ' clk_tb $end
$var reg 1 ( reset_tb $end
$var reg 1 ) sr_in_l_tb $end
$var reg 1 * sr_in_r_tb $end
$var reg 8 + s_tb[7:0] $end
$var reg 1 , sr_out_l_tb $end
$var reg 1 - sr_out_r_tb $end
$scope module uut $end
$var reg 4 . a[3:0] $end
$var reg 4 / b[3:0] $end
$var reg 4 0 sel_fct[3:0] $end
$var reg 4 1 sel_route[3:0] $end
$var reg 2 2 sel_out[1:0] $end
$var reg 1 3 sr_in_l $end
$var reg 1 4 sr_in_r $end
$var reg 8 5 s[7:0] $end
$var reg 1 6 sr_out_l $end
$var reg 1 7 sr_out_r $end
$upscope $end
$scope module controller_inst $end
$var reg 1 8 clk $end
$var reg 1 9 reset $end
$var reg 10 : instr_in[9:0] $end
$var reg 4 ; sel_fct[3:0] $end
$var reg 4 < sel_route[3:0] $end
$var reg 2 = sel_out[1:0] $end
$upscope $end
$upscope $end
$enddefinitions $end
#0
b0000 !
b0000 "
bUUUU #
bUUUU $
bUU %
b0000000000 &
0'
1(
0)
0*
b00000000 +
0,
0-
b0000 .
b0000 /
bUUUU 0
bUUUU 1
bUU 2
03
04
b00000000 5
06
07
08
19
b0000000000 :
bUUUU ;
bUUUU <
bUU =
#5000000
b0000 #
b0000 $
b00 %
1'
b0000 0
b0000 1
b00 2
18
b0000 ;
b0000 <
b00 =
#10000000
0'
08
#12000000
b0011 !
b0100 "
b1001000000 &
0(
b0011 .
b0100 /
09
b1001000000 :
#15000000
b1001 #
1'
b00000111 +
b1001 0
b00000111 5
18
b1001 ;
#20000000
0'
08
#25000000
1'
18
#30000000
0'
08
#32000000
b1100 !
b1010 "
b0101000101 &
b00000110 +
b1100 .
b1010 /
b00000110 5
b0101000101 :
#35000000
b0101 #
b0001 $
b01 %
1'
b00001000 +
b0101 0
b0001 1
b01 2
b00001000 5
18
b0101 ;
b0001 <
b01 =
#40000000
0'
08
#45000000
1'
18
#50000000
0'
08
#52000000
b0111 !
b0010 "
b1010001010 &
b00000010 +
b0111 .
b0010 /
b00000010 5
b1010001010 :
#55000000
b1010 #
b0010 $
b10 %
1'
b00000101 +
b1010 0
b0010 1
b10 2
b00000101 5
18
b1010 ;
b0010 <
b10 =
